gryffin/__init__.py
gryffin/_version.py
gryffin/gryffin.py
gryffin/setup.py
gryffin/acquisition/__init__.py
gryffin/acquisition/acquisition.py
gryffin/acquisition/parameter_optimizer.py
gryffin/acquisition/numpy_optimizers/__init__.py
gryffin/acquisition/numpy_optimizers/abstract_optimizer.py
gryffin/acquisition/numpy_optimizers/adam_optimizer.py
gryffin/acquisition/numpy_optimizers/naive_categorical_optimizer.py
gryffin/acquisition/numpy_optimizers/naive_discrete_optimizer.py
gryffin/bayesian_network/__init__.py
gryffin/bayesian_network/bayesian_network.py
gryffin/bayesian_network/category_reshaper.py
gryffin/bayesian_network/kernel_evaluations.cpython-37m-darwin.so
gryffin/bayesian_network/kernel_prob_reshaping.cpython-37m-darwin.so
gryffin/bayesian_network/model_details.py
gryffin/bayesian_network/edward_interface/__init__.py
gryffin/bayesian_network/edward_interface/_edward_network.py
gryffin/bayesian_network/edward_interface/edward_interface.py
gryffin/bayesian_network/edward_interface/numpy_graph.py
gryffin/bayesian_network/tfprob_interface/__init__.py
gryffin/bayesian_network/tfprob_interface/numpy_graph.py
gryffin/bayesian_network/tfprob_interface/tfprob_interface.py
gryffin/database_handler/__init__.py
gryffin/database_handler/database_handler.py
gryffin/database_handler/db_cache.py
gryffin/database_handler/db_werkzeug.py
gryffin/database_handler/json_writers/__init__.py
gryffin/database_handler/json_writers/db_writer.py
gryffin/database_handler/pandas_writers/__init__.py
gryffin/database_handler/pandas_writers/db_writer.py
gryffin/database_handler/pickle_writers/__init__.py
gryffin/database_handler/pickle_writers/db_writer.py
gryffin/database_handler/sqlite_interface/__init__.py
gryffin/database_handler/sqlite_interface/sqlite_database.py
gryffin/database_handler/sqlite_interface/sqlite_interface.py
gryffin/database_handler/sqlite_interface/sqlite_operations.py
gryffin/descriptor_generator/__init__.py
gryffin/descriptor_generator/descriptor_generator.py
gryffin-0.1.1.dist-info/LICENSE.md
gryffin-0.1.1.dist-info/METADATA
gryffin-0.1.1.dist-info/WHEEL
gryffin-0.1.1.dist-info/top_level.txt
gryffin-0.1.1.dist-info/RECORD
