Metadata-Version: 2.1
Name: gryffin
Version: 0.1.1
Summary: Bayesian optimization for categorical variables
Home-page: https://github.com/aspuru-guzik-group/gryffin
Author: Florian Hase
License: UNKNOWN
Platform: UNKNOWN
Classifier: Intended Audience :: Science/Research
Classifier: Operating System :: Unix
Classifier: Programming Language :: Python
Classifier: Topic :: Scientific/Engineering
Requires-Python: >=3.6
Requires-Dist: numpy
Requires-Dist: Cython
Requires-Dist: sqlalchemy
Requires-Dist: tensorflow (==2.*,>=2.2.0)
Requires-Dist: tensorflow-probability (==0.*,>=0.10.1git)
